recdroidvid/__init__.py
recdroidvid/adb_commands.py
recdroidvid/recdroidvid_main.py
recdroidvid/settings_and_options.py
recdroidvid/utility_functions.py
recdroidvid-0.1.0.dist-info/LICENSE.txt
recdroidvid-0.1.0.dist-info/METADATA
recdroidvid-0.1.0.dist-info/WHEEL
recdroidvid-0.1.0.dist-info/entry_points.txt
recdroidvid-0.1.0.dist-info/top_level.txt
recdroidvid-0.1.0.dist-info/RECORD
