Metadata-Version: 2.1
Name: recdroidvid
Version: 0.1.0
Summary: Record and monitor video on android devices from computer (currently Linux via USB).
Home-page: https://github.com/abarker/recdroidvid
Author: Allen Barker
Author-email: Allen.L.Barker@gmail.com
License: MIT
Keywords: android,linux,usb,remote,adb,video,movie,record,monitor
Classifier: Development Status :: 4 - Beta
Classifier: Intended Audience :: Developers
Classifier: License :: OSI Approved :: MIT License
Classifier: Operating System :: Unix
Classifier: Operating System :: POSIX
Classifier: Operating System :: Microsoft :: Windows
Classifier: Programming Language :: Python
Classifier: Programming Language :: Python :: 3
Classifier: Programming Language :: Python :: Implementation :: CPython
Classifier: Programming Language :: Python :: Implementation :: PyPy
Classifier: Topic :: Utilities
Requires-Python: >=3.6
License-File: LICENSE.txt
Requires-Dist: wheel
